{"strategy": [{"Driver": "HAM", "Stint": 1.0, "Compound": "ULTRASOFT", "LapStart": 1.0, "FinishOrder": 1, "LapEnd": 14.0, "fill": "purple"}, {"Driver": "HAM", "Stint": 2.0, "Compound": "SOFT", "LapStart": 14.0, "FinishOrder": 1, "LapEnd": 53.0, "fill": "yellow"}, {"Driver": "BOT", "Stint": 1.0, "Compound": "ULTRASOFT", "LapStart": 2.0, "FinishOrder": 2, "LapEnd": 12.0, "fill": "purple"}, {"Driver": "BOT", "Stint": 2.0, "Compound": "SOFT", "LapStart": 12.0, "FinishOrder": 2, "LapEnd": 53.0, "fill": "yellow"}, {"Driver": "VET", "Stint": 2.0, "Compound": "SOFT", "LapStart": 13.0, "FinishOrder": 3, "LapEnd": 53.0, "fill": "yellow"}, {"Driver": "VET", "Stint": 1.0, "Compound": "ULTRASOFT", "LapStart": 1.0, "FinishOrder": 3, "LapEnd": 13.0, "fill": "purple"}, {"Driver": "RAI", "Stint": 2.0, "Compound": "SOFT", "LapStart": 18.0, "FinishOrder": 4, "LapEnd": 53.0, "fill": "yellow"}, {"Driver": "RAI", "Stint": 1.0, "Compound": "ULTRASOFT", "LapStart": 1.0, "FinishOrder": 4, "LapEnd": 18.0, "fill": "purple"}, {"Driver": "VER", "Stint": 2.0, "Compound": "ULTRASOFT", "LapStart": 43.0, "FinishOrder": 5, "LapEnd": 53.0, "fill": "purple"}, {"Driver": "VER", "Stint": 1.0, "Compound": "SOFT", "LapStart": 1.0, "FinishOrder": 5, "LapEnd": 43.0, "fill": "yellow"}, {"Driver": "RIC", "Stint": 2.0, "Compound": "ULTRASOFT", "LapStart": 39.0, "FinishOrder": 6, "LapEnd": 53.0, "fill": "purple"}, {"Driver": "RIC", "Stint": 1.0, "Compound": "SOFT", "LapStart": 1.0, "FinishOrder": 6, "LapEnd": 39.0, "fill": "yellow"}, {"Driver": "LEC", "Stint": 2.0, "Compound": "SOFT", "LapStart": 10.0, "FinishOrder": 7, "LapEnd": 53.0, "fill": "yellow"}, {"Driver": "LEC", "Stint": 1.0, "Compound": "HYPERSOFT", "LapStart": 1.0, "FinishOrder": 7, "LapEnd": 10.0, "fill": "pink"}, {"Driver": "MAG", "Stint": 1.0, "Compound": "HYPERSOFT", "LapStart": 1.0, "FinishOrder": 8, "LapEnd": 9.0, "fill": "pink"}, {"Driver": "MAG", "Stint": 2.0, "Compound": "SOFT", "LapStart": 9.0, "FinishOrder": 8, "LapEnd": 52.0, "fill": "yellow"}, {"Driver": "OCO", "Stint": 1.0, "Compound": "HYPERSOFT", "LapStart": 1.0, "FinishOrder": 9, "LapEnd": 10.0, "fill": "pink"}, {"Driver": "OCO", "Stint": 2.0, "Compound": "SOFT", "LapStart": 10.0, "FinishOrder": 9, "LapEnd": 52.0, "fill": "yellow"}, {"Driver": "PER", "Stint": 1.0, "Compound": "HYPERSOFT", "LapStart": 1.0, "FinishOrder": 10, "LapEnd": 12.0, "fill": "pink"}, {"Driver": "PER", "Stint": 2.0, "Compound": "SOFT", "LapStart": 12.0, "FinishOrder": 10, "LapEnd": 52.0, "fill": "yellow"}, {"Driver": "GRO", "Stint": 2.0, "Compound": "SOFT", "LapStart": 8.0, "FinishOrder": 11, "LapEnd": 52.0, "fill": "yellow"}, {"Driver": "GRO", "Stint": 1.0, "Compound": "HYPERSOFT", "LapStart": 1.0, "FinishOrder": 11, "LapEnd": 8.0, "fill": "pink"}, {"Driver": "HUL", "Stint": 1.0, "Compound": "SOFT", "LapStart": 1.0, "FinishOrder": 12, "LapEnd": 35.0, "fill": "yellow"}, {"Driver": "HUL", "Stint": 2.0, "Compound": "ULTRASOFT", "LapStart": 35.0, "FinishOrder": 12, "LapEnd": 52.0, "fill": "purple"}, {"Driver": "ERI", "Stint": 1.0, "Compound": "HYPERSOFT", "LapStart": 1.0, "FinishOrder": 13, "LapEnd": 11.0, "fill": "pink"}, {"Driver": "ERI", "Stint": 3.0, "Compound": "ULTRASOFT", "LapStart": 37.0, "FinishOrder": 13, "LapEnd": 52.0, "fill": "purple"}, {"Driver": "ERI", "Stint": 2.0, "Compound": "SOFT", "LapStart": 11.0, "FinishOrder": 13, "LapEnd": 37.0, "fill": "yellow"}, {"Driver": "ALO", "Stint": 2.0, "Compound": "SOFT", "LapStart": 5.0, "FinishOrder": 14, "LapEnd": 52.0, "fill": "yellow"}, {"Driver": "ALO", "Stint": 1.0, "Compound": "ULTRASOFT", "LapStart": 1.0, "FinishOrder": 14, "LapEnd": 5.0, "fill": "purple"}, {"Driver": "STR", "Stint": 1.0, "Compound": "ULTRASOFT", "LapStart": 1.0, "FinishOrder": 15, "LapEnd": 7.0, "fill": "purple"}, {"Driver": "STR", "Stint": 2.0, "Compound": "SOFT", "LapStart": 7.0, "FinishOrder": 15, "LapEnd": 52.0, "fill": "yellow"}, {"Driver": "VAN", "Stint": 1.0, "Compound": "ULTRASOFT", "LapStart": 1.0, "FinishOrder": 16, "LapEnd": 11.0, "fill": "purple"}, {"Driver": "VAN", "Stint": 2.0, "Compound": "SOFT", "LapStart": 11.0, "FinishOrder": 16, "LapEnd": 51.0, "fill": "yellow"}, {"Driver": "SAI", "Stint": 1.0, "Compound": "SOFT", "LapStart": 1.0, "FinishOrder": 17, "LapEnd": 32.0, "fill": "yellow"}, {"Driver": "SAI", "Stint": 2.0, "Compound": "ULTRASOFT", "LapStart": 32.0, "FinishOrder": 17, "LapEnd": 51.0, "fill": "purple"}, {"Driver": "SIR", "Stint": 1.0, "Compound": "ULTRASOFT", "LapStart": 1.0, "FinishOrder": 18, "LapEnd": 10.0, "fill": "purple"}, {"Driver": "SIR", "Stint": 2.0, "Compound": "SOFT", "LapStart": 10.0, "FinishOrder": 18, "LapEnd": 51.0, "fill": "yellow"}, {"Driver": "GAS", "Stint": 1.0, "Compound": "SOFT", "LapStart": 1.0, "FinishOrder": 19, "LapEnd": 4.0, "fill": "yellow"}, {"Driver": "HAR", "Stint": 1.0, "Compound": "HYPERSOFT", "LapStart": 1.0, "FinishOrder": 20, "LapEnd": 3.0, "fill": "pink"}, {"Driver": "HAR", "Stint": 2.0, "Compound": "SOFT", "LapStart": 3.0, "FinishOrder": 20, "LapEnd": 4.0, "fill": "yellow"}]}