{"fastest": [{"Driver": "VET", "LapTime": 91.095, "Diff": 0.0, "Team": "Ferrari"}, {"Driver": "RAI", "LapTime": 91.182, "Diff": 0.087, "Team": "Ferrari"}, {"Driver": "BOT", "LapTime": 91.625, "Diff": 0.53, "Team": "Mercedes"}, {"Driver": "HAM", "LapTime": 91.675, "Diff": 0.58, "Team": "Mercedes"}, {"Driver": "VER", "LapTime": 91.796, "Diff": 0.701, "Team": "Red Bull Racing"}, {"Driver": "RIC", "LapTime": 91.948, "Diff": 0.853, "Team": "Red Bull Racing"}, {"Driver": "HUL", "LapTime": 92.494, "Diff": 1.399, "Team": "Renault"}, {"Driver": "GRO", "LapTime": 92.524, "Diff": 1.429, "Team": "Haas F1 Team"}, {"Driver": "PER", "LapTime": 92.758, "Diff": 1.663, "Team": "Force India"}, {"Driver": "SAI", "LapTime": 92.819, "Diff": 1.724, "Team": "Renault"}, {"Driver": "MAG", "LapTime": 92.986, "Diff": 1.891, "Team": "Haas F1 Team"}, {"Driver": "OCO", "LapTime": 93.057, "Diff": 1.962, "Team": "Force India"}, {"Driver": "ALO", "LapTime": 93.232, "Diff": 2.137, "Team": "McLaren"}, {"Driver": "VAN", "LapTime": 93.505, "Diff": 2.41, "Team": "McLaren"}, {"Driver": "HAR", "LapTime": 93.795, "Diff": 2.7, "Team": "Toro Rosso"}, {"Driver": "SIR", "LapTime": 94.062, "Diff": 2.967, "Team": "Williams"}, {"Driver": "GAS", "LapTime": 94.101, "Diff": 3.006, "Team": "Toro Rosso"}, {"Driver": "STR", "LapTime": 94.285, "Diff": 3.19, "Team": "Williams"}, {"Driver": "LEC", "LapTime": 94.454, "Diff": 3.359, "Team": "Sauber"}, {"Driver": "ERI", "LapTime": 94.914, "Diff": 3.819, "Team": "Sauber"}]}